icims_a11y_tools/__init__.py
icims_a11y_tools-0.0.5.dist-info/METADATA
icims_a11y_tools-0.0.5.dist-info/WHEEL
icims_a11y_tools-0.0.5.dist-info/top_level.txt
icims_a11y_tools-0.0.5.dist-info/RECORD
