Metadata-Version: 2.1
Name: icims-a11y-tools
Version: 0.0.5
Summary: The icims a11y scanner package
Home-page: UNKNOWN
Author: chrisding
Author-email: UNKNOWN
License: UNKNOWN
Platform: UNKNOWN
Classifier: Programming Language :: Python :: 3
Classifier: License :: OSI Approved :: MIT License
Classifier: Operating System :: OS Independent
